dapla/__init__.py
dapla/execute.py
dapla/jupyterextensions/__init__.py
dapla/jupyterextensions/authenticator.py
dapla/jupyterextensions/authextension.py
dapla/magics/__init__.py
dapla/magics/documentation.py
dapla/magics/lineage.py
dapla/services/__init__.py
dapla/services/clients.py
dapla/services/gcs.py
dapla/services/reader.py
dapla/services/writer.py
dapla/spark/__init__.py
dapla/spark/decorators.py
dapla/spark/sparkextension.py
dapla/spark/sparkui.py
ssb_ipython_kernels-0.3.3.dist-info/LICENSE
ssb_ipython_kernels-0.3.3.dist-info/METADATA
ssb_ipython_kernels-0.3.3.dist-info/WHEEL
ssb_ipython_kernels-0.3.3.dist-info/top_level.txt
ssb_ipython_kernels-0.3.3.dist-info/RECORD
