Metadata-Version: 2.1
Name: ssb-ipython-kernels
Version: 0.3.3
Summary: Jupyter kernels for working with dapla services
Home-page: https://github.com/statisticsnorway/dapla-ipython-kernels
Author: Statistics Norway
Author-email: bjorn.skaar@ssb.no
License: MIT
Platform: UNKNOWN
Classifier: Development Status :: 2 - Pre-Alpha
Classifier: License :: OSI Approved :: MIT License
Classifier: Programming Language :: Python :: 3.6
Classifier: Programming Language :: Python :: 3.7
Classifier: Programming Language :: Python :: 3.8
Requires-Dist: ipython (>=7.22.0)
Requires-Dist: pyspark (>=3.1.1)
Requires-Dist: jupyterhub (>=1.3.0)
Requires-Dist: oauthenticator (>=14.0.0)
Requires-Dist: requests (==2.25.1)
Requires-Dist: requests-cache (==0.5.2)
Requires-Dist: responses (==0.13.2)
Requires-Dist: ipykernel (>=5.5.3)
Requires-Dist: notebook (>=6.3.0)
Requires-Dist: tornado (>=6.1)
Requires-Dist: gcsfs (==0.6.2)
Requires-Dist: pyarrow (>=4.0.1)
Requires-Dist: pandas (>=1.2.5)
Requires-Dist: google-auth (>=1.28.1)
Requires-Dist: google-auth-oauthlib (>=0.4.4)
Requires-Dist: ipywidgets (>=7.6.3)
Requires-Dist: pyjwt (>=2.0.1)
